osm2pgsql_tuner/__init__.py
osm2pgsql_tuner/tuner.py
osm2pgsql_tuner-0.1.0.dist-info/LICENSE
osm2pgsql_tuner-0.1.0.dist-info/METADATA
osm2pgsql_tuner-0.1.0.dist-info/WHEEL
osm2pgsql_tuner-0.1.0.dist-info/top_level.txt
osm2pgsql_tuner-0.1.0.dist-info/RECORD
