Metadata-Version: 2.1
Name: osm2pgsql-tuner
Version: 0.1.0
Summary: osm2pgsql-tuner project recommends an osm2pgsql command based on available system resources and the size of the input PBF file.
Home-page: https://github.com/rustprooflabs/osm2pgsql-tuner
Author: RustProof Labs
Author-email: RustProof Labs <support@rustprooflabs.com>
Project-URL: Homepage, https://github.com/rustprooflabs/osm2pgsql-tuner
Project-URL: Issues, https://github.com/rustprooflabs/osm2pgsql-tuner/issues
Classifier: Programming Language :: Python :: 3
Classifier: License :: OSI Approved :: MIT License
Classifier: Operating System :: OS Independent
Requires-Python: >=3.8
License-File: LICENSE
